utils.py
create_flask_app/__init__.py
create_flask_app/__main__.py
create_flask_app/cli.py
create_flask_app/api/requirements.txt
create_flask_app/api/run.py
create_flask_app/api/app/__init__.py
create_flask_app/api/app/config.py
create_flask_app/api/app/errors/__init__.py
create_flask_app/api/app/errors/handlers.py
create_flask_app/api/app/some_blueprint/__init__.py
create_flask_app/api/app/some_blueprint/routes.py
create_flask_app/default/requirements.txt
create_flask_app/default/run.py
create_flask_app/default/app/__init__.py
create_flask_app/default/app/config.py
create_flask_app/default/app/errors/__init__.py
create_flask_app/default/app/errors/handlers.py
create_flask_app/default/app/home/__init__.py
create_flask_app/default/app/home/routes.py
create_flask_app/default/app/static/css/main.css
create_flask_app/default/app/templates/about.html
create_flask_app/default/app/templates/base.html
create_flask_app/default/app/templates/error.html
create_flask_app/default/app/templates/home.html
create_flask_app/helloworld/app.py
create_flask_app/spa/requirements.txt
create_flask_app/spa/run.py
create_flask_app/spa/app/__init__.py
create_flask_app/spa/app/config.py
create_flask_app/spa/app/errors/__init__.py
create_flask_app/spa/app/errors/handlers.py
create_flask_app/spa/app/home/__init__.py
create_flask_app/spa/app/home/routes.py
create_flask_app/spa/app/static/css/main.css
create_flask_app/spa/app/static/js/button.js
create_flask_app/spa/app/templates/base.html
create_flask_app/spa/app/templates/home.html
createflaskapp-1.2.dist-info/LICENSE
createflaskapp-1.2.dist-info/METADATA
createflaskapp-1.2.dist-info/WHEEL
createflaskapp-1.2.dist-info/entry_points.txt
createflaskapp-1.2.dist-info/top_level.txt
createflaskapp-1.2.dist-info/RECORD
