Metadata-Version: 2.1
Name: createflaskapp
Version: 1.2
Summary: Package for initializing a flask project structure
Home-page: https://github.com/isakal/create-flask-app
Author: Ivan Sakal
Author-email: sakalivan4@gmail.com
License: MIT
Platform: UNKNOWN
Classifier: Programming Language :: Python :: 3
Classifier: Programming Language :: Python :: 3.6
Classifier: Programming Language :: Python :: 3.7
Classifier: License :: OSI Approved :: MIT License
Classifier: Operating System :: OS Independent
Requires-Python: >=3.6
Requires-Dist: Click (>=7)
Requires-Dist: animation (>=0.0.6)
Requires-Dist: termcolor (>=1.1.0)
